[{"line":1,"elements":[{"start_timestamp":"2022-05-11T23:14:25.955Z","line":3,"name":"Validate Free CRM Home Page Test","description":"","id":"free-crm-application-test;validate-free-crm-home-page-test","type":"scenario","keyword":"Scenario","steps":[{"result":{"duration":28904000000,"status":"passed"},"line":5,"name":"user opens browser","match":{"location":"com.qa.stepDefinitions.HomePageSteps.user_opens_browser()"},"keyword":"Given "},{"result":{"duration":46000000,"status":"passed"},"line":6,"name":"user is on login page","match":{"location":"com.qa.stepDefinitions.HomePageSteps.user_is_on_login_page()"},"keyword":"Then "},{"result":{"duration":31043000000,"status":"passed"},"line":7,"name":"user logs into app","match":{"location":"com.qa.stepDefinitions.HomePageSteps.user_enters_username_and_password()"},"keyword":"Then "},{"result":{"duration":6527000000,"status":"passed"},"line":8,"name":"home page is displayed","match":{"location":"com.qa.stepDefinitions.HomePageSteps.home_page_is_displayed()"},"keyword":"Then "},{"result":{"error_message":"org.openqa.selenium.NoSuchElementException: no such element: Unable to locate element: {\"method\":\"xpath\",\"selector\":\"//td[contains(text(),'User: Naveen K')]\"}\n  (Session info: chrome=101.0.4951.64)\nFor documentation on this error, please visit: http://seleniumhq.org/exceptions/no_such_element.html\nBuild info: version: '3.11.0', revision: 'e59cfb3', time: '2018-03-11T20:26:55.152Z'\nSystem info: host: 'BALACHANDAR-LP1', ip: '172.20.9.97', os.name: 'Windows 10', os.arch: 'amd64', os.version: '10.0', java.version: '1.8.0_333'\nDriver info: org.openqa.selenium.chrome.ChromeDriver\nCapabilities {acceptInsecureCerts: false, browserName: chrome, browserVersion: 101.0.4951.64, chrome: {chromedriverVersion: 101.0.4951.41 (93c720db8323..., userDataDir: C:\\Users\\BALACH~1.K\\AppData...}, goog:chromeOptions: {debuggerAddress: localhost:53469}, javascriptEnabled: true, networkConnectionEnabled: false, pageLoadStrategy: normal, platform: WINDOWS, platformName: WINDOWS, proxy: Proxy(), setWindowRect: true, strictFileInteractability: false, timeouts: {implicit: 0, pageLoad: 300000, script: 30000}, unhandledPromptBehavior: dismiss and notify, webauthn:extension:credBlob: true, webauthn:extension:largeBlob: true, webauthn:virtualAuthenticators: true}\nSession ID: e9cda7c26a9c4742e90e2530bdf60adc\n*** Element info: {Using=xpath, value=//td[contains(text(),'User: Naveen K')]}\r\n\tat sun.reflect.NativeConstructorAccessorImpl.newInstance0(Native Method)\r\n\tat sun.reflect.NativeConstructorAccessorImpl.newInstance(Unknown Source)\r\n\tat sun.reflect.DelegatingConstructorAccessorImpl.newInstance(Unknown Source)\r\n\tat java.lang.reflect.Constructor.newInstance(Unknown Source)\r\n\tat org.openqa.selenium.remote.http.W3CHttpResponseCodec.createException(W3CHttpResponseCodec.java:187)\r\n\tat org.openqa.selenium.remote.http.W3CHttpResponseCodec.decode(W3CHttpResponseCodec.java:122)\r\n\tat org.openqa.selenium.remote.http.W3CHttpResponseCodec.decode(W3CHttpResponseCodec.java:49)\r\n\tat org.openqa.selenium.remote.HttpCommandExecutor.execute(HttpCommandExecutor.java:158)\r\n\tat org.openqa.selenium.remote.service.DriverCommandExecutor.execute(DriverCommandExecutor.java:83)\r\n\tat org.openqa.selenium.remote.RemoteWebDriver.execute(RemoteWebDriver.java:545)\r\n\tat org.openqa.selenium.remote.RemoteWebDriver.findElement(RemoteWebDriver.java:319)\r\n\tat org.openqa.selenium.remote.RemoteWebDriver.findElementByXPath(RemoteWebDriver.java:421)\r\n\tat org.openqa.selenium.By$ByXPath.findElement(By.java:361)\r\n\tat org.openqa.selenium.remote.RemoteWebDriver.findElement(RemoteWebDriver.java:311)\r\n\tat org.openqa.selenium.support.pagefactory.DefaultElementLocator.findElement(DefaultElementLocator.java:69)\r\n\tat org.openqa.selenium.support.pagefactory.internal.LocatingElementHandler.invoke(LocatingElementHandler.java:38)\r\n\tat com.sun.proxy.$Proxy16.isDisplayed(Unknown Source)\r\n\tat com.qa.pages.HomePage.verifyCorrectUSerName(HomePage.java:41)\r\n\tat com.qa.stepDefinitions.HomePageSteps.validate_logged_in_user_name(HomePageSteps.java:42)\r\n\tat ✽.validate logged in user name(file:///C:/Users/balachandar.k/eclipse-workspace/CucumberMavenPOM/src/main/java/com/qa/features/freecrm.feature:9)\r\n","duration":99000000,"status":"failed"},"line":9,"name":"validate logged in user name","match":{"location":"com.qa.stepDefinitions.HomePageSteps.validate_logged_in_user_name()"},"keyword":"Then "}]}],"name":"Free CRM Application Test","description":"","id":"free-crm-application-test","keyword":"Feature","uri":"file:src/main/java/com/qa/features/freecrm.feature","tags":[]}]